talktollm/__init__.py
talktollm/__main__.py
talktollm/images/aistudio/8192.png
talktollm/images/aistudio/aistudio.png
talktollm/images/aistudio/aistudio2.png
talktollm/images/aistudio/chrome.png
talktollm/images/aistudio/cop4.png
talktollm/images/aistudio/copy.png
talktollm/images/aistudio/copy2.png
talktollm/images/aistudio/copyimage.png
talktollm/images/aistudio/copyorsmthn.png
talktollm/images/aistudio/done.png
talktollm/images/aistudio/message.png
talktollm/images/aistudio/message2.png
talktollm/images/aistudio/orcopy.png
talktollm/images/aistudio/ormessage.png
talktollm/images/aistudio/ratelimit.png
talktollm/images/aistudio/realrundark.png
talktollm/images/aistudio/run.png
talktollm/images/aistudio/rundark.png
talktollm/images/aistudio/runsmthn.png
talktollm/images/aistudio/scroll.png
talktollm/images/aistudio/thatnumagain.png
talktollm/images/aistudio/thinking.png
talktollm/images/aistudio/type3.png
talktollm/images/aistudio/typenew.png
talktollm/images/aistudio/typeplz.png
talktollm/images/aistudio/typeytype.png
talktollm/images/aistudio/tyre.png
talktollm/images/deepseek/chrome.png
talktollm/images/deepseek/copy.png
talktollm/images/deepseek/message.png
talktollm/images/deepseek/run.png
talktollm/images/gemini/chrome.png
talktollm/images/gemini/copy.png
talktollm/images/gemini/copy2.png
talktollm/images/gemini/message.png
talktollm/images/gemini/message2.png
talktollm/images/gemini/orcopy.png
talktollm/images/gemini/run.png
talktollm/images/gemini/send.png
talktollm-0.8.0.dist-info/licenses/LICENSE
talktollm-0.8.0.dist-info/METADATA
talktollm-0.8.0.dist-info/WHEEL
talktollm-0.8.0.dist-info/entry_points.txt
talktollm-0.8.0.dist-info/top_level.txt
talktollm-0.8.0.dist-info/RECORD
