Metadata-Version: 2.4
Name: talktollm
Version: 0.8.0
Summary: A Python utility for interacting with large language models (LLMs) via web automation
Home-page: https://github.com/AMAMazing/talktollm
Author: Alex M
Author-email: alexmalone489@gmail.com
Keywords: llm,automation,gui,pyautogui,gemini,deepseek,clipboard,aistudio
Classifier: Programming Language :: Python :: 3
Classifier: License :: OSI Approved :: MIT License
Classifier: Operating System :: Microsoft :: Windows
Classifier: Development Status :: 4 - Beta
Classifier: Intended Audience :: Developers
Classifier: Topic :: Communications :: Chat
Classifier: Topic :: Scientific/Engineering :: Image Recognition
Requires-Python: >=3.6
License-File: LICENSE
Requires-Dist: pywin32
Requires-Dist: pyautogui
Requires-Dist: pillow
Requires-Dist: optimisewait
Dynamic: author
Dynamic: author-email
Dynamic: classifier
Dynamic: description
Dynamic: description-content-type
Dynamic: home-page
Dynamic: keywords
Dynamic: license-file
Dynamic: requires-dist
Dynamic: requires-python
Dynamic: summary
